odoo/addons/agreement_helpdesk_mgmt_sale/README.rst
odoo/addons/agreement_helpdesk_mgmt_sale/__init__.py
odoo/addons/agreement_helpdesk_mgmt_sale/__manifest__.py
odoo/addons/agreement_helpdesk_mgmt_sale/i18n/agreement_helpdesk_mgmt_sale.pot
odoo/addons/agreement_helpdesk_mgmt_sale/i18n/it.po
odoo/addons/agreement_helpdesk_mgmt_sale/i18n/sv.po
odoo/addons/agreement_helpdesk_mgmt_sale/models/__init__.py
odoo/addons/agreement_helpdesk_mgmt_sale/models/helpdesk_ticket.py
odoo/addons/agreement_helpdesk_mgmt_sale/readme/CONTRIBUTORS.md
odoo/addons/agreement_helpdesk_mgmt_sale/readme/DESCRIPTION.md
odoo/addons/agreement_helpdesk_mgmt_sale/static/description/icon.png
odoo/addons/agreement_helpdesk_mgmt_sale/static/description/index.html
odoo/addons/agreement_helpdesk_mgmt_sale/tests/__init__.py
odoo/addons/agreement_helpdesk_mgmt_sale/tests/test_agreement_helpdesk_mgmt_sale.py
odoo_addon_agreement_helpdesk_mgmt_sale-18.0.1.0.0.6.dist-info/METADATA
odoo_addon_agreement_helpdesk_mgmt_sale-18.0.1.0.0.6.dist-info/WHEEL
odoo_addon_agreement_helpdesk_mgmt_sale-18.0.1.0.0.6.dist-info/top_level.txt
odoo_addon_agreement_helpdesk_mgmt_sale-18.0.1.0.0.6.dist-info/RECORD
