Metadata-Version: 2.1
Name: odoo-addon-agreement_helpdesk_mgmt_sale
Version: 18.0.1.0.0.6
Requires-Python: >=3.10
Requires-Dist: odoo-addon-agreement_helpdesk_mgmt==18.0.*
Requires-Dist: odoo-addon-agreement_sale==18.0.*
Requires-Dist: odoo-addon-helpdesk_mgmt_sale==18.0.*
Requires-Dist: odoo==18.0.*
Summary: Agreement Helpdesk Mgmt Sale
Home-page: https://github.com/OCA/agreement
License: AGPL-3
Author: Camptocamp, Odoo Community Association (OCA)
Author-email: support@odoo-community.org
Classifier: Programming Language :: Python
Classifier: Framework :: Odoo
Classifier: Framework :: Odoo :: 18.0
Classifier: License :: OSI Approved :: GNU Affero General Public License v3
